domb_napari/__init__.py
domb_napari/_widget.py
domb_napari/napari.yaml
domb_napari-2024.2.29.dist-info/LICENSE
domb_napari-2024.2.29.dist-info/METADATA
domb_napari-2024.2.29.dist-info/WHEEL
domb_napari-2024.2.29.dist-info/entry_points.txt
domb_napari-2024.2.29.dist-info/top_level.txt
domb_napari-2024.2.29.dist-info/RECORD
