Metadata-Version: 2.1
Name: domb-napari
Version: 2024.2.29
Summary: napari plugin for analyzing fluorescence-labeled proteins redistribution
Author: Borys Olifirov
Author-email: omnia.fatum@gmail.com
License: MIT
Project-URL: Documentation, https://domb.bio/
Project-URL: Source Code, https://github.com/wisstock/domb-napari
Project-URL: Bug Tracker, https://github.com/wisstock/domb-napari/issues
Project-URL: User Support, https://github.com/wisstock/domb-napari/issues
Classifier: Framework :: napari
Classifier: Development Status :: 3 - Alpha
Classifier: License :: OSI Approved :: MIT License
Classifier: Programming Language :: Python :: 3.8
Classifier: Programming Language :: Python :: 3.9
Classifier: Programming Language :: Python :: 3.10
Classifier: Programming Language :: Python :: 3.11
Classifier: Operating System :: OS Independent
Classifier: Topic :: Scientific/Engineering :: Bio-Informatics
Classifier: Topic :: Scientific/Engineering :: Image Processing
Classifier: Topic :: Scientific/Engineering :: Image Recognition
Classifier: Topic :: Utilities
Requires-Python: >=3.8
License-File: LICENSE
Requires-Dist: napari
Requires-Dist: domb
